openghg/__init__.py
openghg/_version.py
openghg/analyse/__init__.py
openghg/analyse/_footprint.py
openghg/analyse/_scenario.py
openghg/client/__init__.py
openghg/client/_jobrunner.py
openghg/client/_observations.py
openghg/client/_process.py
openghg/client/_rank_sources.py
openghg/client/_search.py
openghg/client/_test_service.py
openghg/client/_user.py
openghg/data/README
openghg/data/acrg_obs_scale_convert.csv
openghg/data/acrg_site_info.json
openghg/data/acrg_species_info.json
openghg/data/acrg_with_locations.json
openghg/data/attributes.json
openghg/data/beaco2n_site_data.json
openghg/data/ceda_compliance.json
openghg/data/colour_maps.json
openghg/data/ecmwf_dataset_info.json
openghg/data/icos_eurocom_sites.json
openghg/data/lghg_data.json
openghg/data/name_code_lookup.json
openghg/data/noaa_data.json
openghg/data/noaa_sites.json
openghg/data/process_gcwerks_parameters.json
openghg/data/process_gcwerks_parameters_bp1.json
openghg/data/site_codes.json
openghg/data/site_longname.json
openghg/data/site_lookup.json
openghg/data/species_attributes.json
openghg/data/species_translator.json
openghg/dataobjects/__init__.py
openghg/dataobjects/_basedata.py
openghg/dataobjects/_flux_data.py
openghg/dataobjects/_footprint_data.py
openghg/dataobjects/_metdata.py
openghg/dataobjects/_obsdata.py
openghg/dataobjects/_ranksources.py
openghg/dataobjects/_searchresults.py
openghg/jobs/__init__.py
openghg/jobs/_create.py
openghg/jobs/_jobdrive.py
openghg/jobs/_run.py
openghg/jobs/_sshconnect.py
openghg/objectstore/__init__.py
openghg/objectstore/_local_store.py
openghg/objectstore/_openghg_objstore.py
openghg/plotting/__init__.py
openghg/plotting/_footprint.py
openghg/retrieve/__init__.py
openghg/retrieve/_access.py
openghg/retrieve/_export.py
openghg/retrieve/_search.py
openghg/retrieve/met/__init__.py
openghg/retrieve/met/_ecmwf.py
openghg/service/__init__.py
openghg/service/_errors.py
openghg/service/_openghg_service.py
openghg/standardise/__init__.py
openghg-1.0.0.dist-info/LICENSE
openghg-1.0.0.dist-info/METADATA
openghg-1.0.0.dist-info/WHEEL
openghg-1.0.0.dist-info/top_level.txt
openghg-1.0.0.dist-info/RECORD
