Metadata-Version: 2.1
Name: openghg
Version: 1.0.0
Summary: OpenGHG - a cloud platform for greenhouse gas data analysis
Home-page: https://github.com/openghg/openghg
Author: Gareth Jones
Author-email: g.m.jones@bristol.ac.uk
License: Apache
Project-URL: Documentation, https://www.openghg.org
Project-URL: Code, https://github.com/openghg/openghg
Project-URL: Issue tracker, https://github.com/openghg/openghg/issues
Platform: UNKNOWN
Classifier: Programming Language :: Python :: 3.7
Classifier: Programming Language :: Python :: 3.8
Classifier: Programming Language :: Python :: 3.9
Classifier: Programming Language :: Python :: 3.10
Classifier: License :: OSI Approved :: Apache Software License
Classifier: Operating System :: POSIX :: Linux
Classifier: Operating System :: MacOS
Requires-Python: >=3.7
License-File: LICENSE
Requires-Dist: addict
Requires-Dist: cdsapi
Requires-Dist: dask
Requires-Dist: lazy-import
Requires-Dist: matplotlib
Requires-Dist: netcdf4
Requires-Dist: numexpr
Requires-Dist: numpy
Requires-Dist: nc-time-axis
Requires-Dist: pandas
Requires-Dist: paramiko
Requires-Dist: plotly
Requires-Dist: pyvis
Requires-Dist: rapidfuzz
Requires-Dist: requests (>=2.25)
Requires-Dist: scipy
Requires-Dist: tqdm
Requires-Dist: xarray (>=0.18.2)
Requires-Dist: urllib3 (>=1.26.3)
